random_time_with_intervals/__init__.py
random_time_with_intervals/Time_interval_thing.py
random_time_with_intervals-0.1.0.dist-info/WHEEL
random_time_with_intervals-0.1.0.dist-info/METADATA
random_time_with_intervals-0.1.0.dist-info/RECORD
