Metadata-Version: 2.1
Name: random-time-with-intervals
Version: 0.1.0
Summary: 
Author: Your Name
Author-email: you@example.com
Requires-Python: >=3.10,<4.0
Classifier: Programming Language :: Python :: 3
Classifier: Programming Language :: Python :: 3.10
Requires-Dist: XlsxWriter (>=3.0.3,<4.0.0)
